LICENSE
README.rst
setup.py
LMRt/__init__.py
LMRt/da.py
LMRt/gridded.py
LMRt/proxy.py
LMRt/psm.py
LMRt/reconjob.py
LMRt/reconres.py
LMRt/utils.py
LMRt/visual.py
LMRt.egg-info/PKG-INFO
LMRt.egg-info/SOURCES.txt
LMRt.egg-info/dependency_links.txt
LMRt.egg-info/not-zip-safe
LMRt.egg-info/requires.txt
LMRt.egg-info/top_level.txt
bin/LMRt