Metadata-Version: 2.1
Name: LMRt
Version: 0.8.5
Summary: LMR turbo
Home-page: https://github.com/fzhu2e/LMRt
Author: Feng Zhu
Author-email: fengzhu@usc.edu
License: GPL-3.0 license
Keywords: LMRt
Platform: UNKNOWN
Classifier: Natural Language :: English
Classifier: Programming Language :: Python :: 3.8
Classifier: Programming Language :: Python :: 3.9
License-File: LICENSE
